LICENSE
MANIFEST.in
README.md
requirements.pip
setup.py
il2ds_difficulty/__init__.py
il2ds_difficulty/constants.py
il2ds_difficulty/helpers.py
il2ds_difficulty/validators.py
il2ds_difficulty.egg-info/PKG-INFO
il2ds_difficulty.egg-info/SOURCES.txt
il2ds_difficulty.egg-info/dependency_links.txt
il2ds_difficulty.egg-info/requires.txt
il2ds_difficulty.egg-info/top_level.txt
il2ds_difficulty/locale/en/LC_MESSAGES/django.mo
il2ds_difficulty/locale/en/LC_MESSAGES/django.po
il2ds_difficulty/locale/ru/LC_MESSAGES/django.mo
il2ds_difficulty/locale/ru/LC_MESSAGES/django.po