Metadata-Version: 1.1
Name: il2ds-difficulty
Version: 1.0.0
Summary: Convert integer value of IL-2 DS difficulty into informative dictionary.
Home-page: https://github.com/IL2HorusTeam/il2ds-difficulty/
Author: Alexander Oblovatniy, Alexander Kamyhin
Author-email: oblovatniy@gmail.com, kamyhin@gmail.com
License: BSD License
Platform: UNKNOWN
Classifier: Development Status :: 5 - Production/Stable
Classifier: Intended Audience :: Developers
Classifier: Environment :: Web Environment
Classifier: Environment :: Console
Classifier: License :: Free for non-commercial use
Classifier: License :: OSI Approved :: BSD License
Classifier: Natural Language :: English
Classifier: Operating System :: OS Independent
Classifier: Programming Language :: Python :: 2.7
Classifier: Topic :: Software Development :: Libraries
Classifier: Framework :: Django
